gfn/__init__.py
gfn/_version.py
gfn/gfn.py
gfn/nn_lookup.py
gfn_layer-0.1.0.dist-info/METADATA
gfn_layer-0.1.0.dist-info/WHEEL
gfn_layer-0.1.0.dist-info/top_level.txt
gfn_layer-0.1.0.dist-info/RECORD
