Metadata-Version: 2.4
Name: gfn-layer
Version: 0.1.0
Summary: Graph Feedforward Networks: an extension of linear layers to graphs
Author-email: "Oisín M. Morrison" <oisinmmm@gmail.com>
Maintainer-email: "Oisín M. Morrison" <oisinmmm@gmail.com>
License: Apache License Version 2.0
Project-URL: repository, https://github.com/Oisin-M/gfn
Project-URL: documentation, https://gfn-layer.readthedocs.io
Project-URL: issues, https://github.com/Oisin-M/gfn/issues
Classifier: Development Status :: 4 - Beta
Classifier: Intended Audience :: Science/Research
Classifier: Natural Language :: English
Classifier: License :: OSI Approved :: Apache Software License
Classifier: Operating System :: OS Independent
Classifier: Programming Language :: Python :: 3 :: Only
Classifier: Programming Language :: Python :: 3.10
Classifier: Programming Language :: Python :: 3.11
Classifier: Programming Language :: Python :: 3.12
Classifier: Programming Language :: Python :: 3.13
Classifier: Programming Language :: Python :: 3.14
Classifier: Topic :: Scientific/Engineering :: Artificial Intelligence
Requires-Python: >=3.10
Requires-Dist: torch
Requires-Dist: numpy
Requires-Dist: scipy
